altspell_universal_lojikl_inglish/__init__.py
altspell_universal_lojikl_inglish/translate.py
altspell_universal_lojikl_inglish/data/universal-lojikl-inglish-dict.csv
altspell_universal_lojikl_inglish-0.3.0.dist-info/WHEEL
altspell_universal_lojikl_inglish-0.3.0.dist-info/METADATA
altspell_universal_lojikl_inglish-0.3.0.dist-info/RECORD
